aliyunsdkdytnsapi/__init__.py
aliyunsdkdytnsapi/endpoint.py
aliyunsdkdytnsapi/request/__init__.py
aliyunsdkdytnsapi/request/v20200217/DescribeEmptyNumberRequest.py
aliyunsdkdytnsapi/request/v20200217/DescribePhoneNumberAnalysisRequest.py
aliyunsdkdytnsapi/request/v20200217/DescribePhoneNumberOnlineTimeRequest.py
aliyunsdkdytnsapi/request/v20200217/DescribePhoneNumberOperatorAttributeRequest.py
aliyunsdkdytnsapi/request/v20200217/DescribePhoneTwiceTelVerifyRequest.py
aliyunsdkdytnsapi/request/v20200217/InvalidPhoneNumberFilterRequest.py
aliyunsdkdytnsapi/request/v20200217/PhoneNumberEncryptRequest.py
aliyunsdkdytnsapi/request/v20200217/PhoneNumberStatusForAccountRequest.py
aliyunsdkdytnsapi/request/v20200217/PhoneNumberStatusForPublicRequest.py
aliyunsdkdytnsapi/request/v20200217/PhoneNumberStatusForRealRequest.py
aliyunsdkdytnsapi/request/v20200217/PhoneNumberStatusForSmsRequest.py
aliyunsdkdytnsapi/request/v20200217/PhoneNumberStatusForVirtualRequest.py
aliyunsdkdytnsapi/request/v20200217/PhoneNumberStatusForVoiceRequest.py
aliyunsdkdytnsapi/request/v20200217/ThreeElementsVerificationRequest.py
aliyunsdkdytnsapi/request/v20200217/TwoElementsVerificationRequest.py
aliyunsdkdytnsapi/request/v20200217/__init__.py
aliyun_python_sdk_dytnsapi-1.1.8.dist-info/LICENSE
aliyun_python_sdk_dytnsapi-1.1.8.dist-info/METADATA
aliyun_python_sdk_dytnsapi-1.1.8.dist-info/WHEEL
aliyun_python_sdk_dytnsapi-1.1.8.dist-info/top_level.txt
aliyun_python_sdk_dytnsapi-1.1.8.dist-info/RECORD
